{
    "description": "TYPE: CUSTOM\nMaterial Theme Builder export 2025-08-11 12:24:50",
    "seed": "#7C61FF",
    "coreColors": {
        "primary": "#7C61FF"
    },
    "extendedColors": [],
    "schemes": {
        "light": {
            "primary": "#5F5790",
            "surfaceTint": "#5F5790",
            "onPrimary": "#FFFFFF",
            "primaryContainer": "#E5DEFF",
            "onPrimaryContainer": "#473F77",
            "secondary": "#605C71",
            "onSecondary": "#FFFFFF",
            "secondaryContainer": "#E5DFF9",
            "onSecondaryContainer": "#484459",
            "tertiary": "#7C5264",
            "onTertiary": "#FFFFFF",
            "tertiaryContainer": "#FFD8E6",
            "onTertiaryContainer": "#623B4C",
            "error": "#BA1A1A",
            "onError": "#FFFFFF",
            "errorContainer": "#FFDAD6",
            "onErrorContainer": "#93000A",
            "background": "#FDF8FF",
            "onBackground": "#1C1B20",
            "surface": "#FDF8FF",
            "onSurface": "#1C1B20",
            "surfaceVariant": "#E5E0EC",
            "onSurfaceVariant": "#48454E",
            "outline": "#79757F",
            "outlineVariant": "#C9C5D0",
            "shadow": "#000000",
            "scrim": "#000000",
            "inverseSurface": "#312F36",
            "inverseOnSurface": "#F4EFF7",
            "inversePrimary": "#C9BFFF",
            "primaryFixed": "#E5DEFF",
            "onPrimaryFixed": "#1B1149",
            "primaryFixedDim": "#C9BFFF",
            "onPrimaryFixedVariant": "#473F77",
            "secondaryFixed": "#E5DFF9",
            "onSecondaryFixed": "#1C192B",
            "secondaryFixedDim": "#C9C3DC",
            "onSecondaryFixedVariant": "#484459",
            "tertiaryFixed": "#FFD8E6",
            "onTertiaryFixed": "#301120",
            "tertiaryFixedDim": "#EDB8CD",
            "onTertiaryFixedVariant": "#623B4C",
            "surfaceDim": "#DDD8E0",
            "surfaceBright": "#FDF8FF",
            "surfaceContainerLowest": "#FFFFFF",
            "surfaceContainerLow": "#F7F2FA",
            "surfaceContainer": "#F1ECF4",
            "surfaceContainerHigh": "#EBE6EE",
            "surfaceContainerHighest": "#E5E1E9"
        },
        "light-medium-contrast": {
            "primary": "#372E65",
            "surfaceTint": "#5F5790",
            "onPrimary": "#FFFFFF",
            "primaryContainer": "#6E65A0",
            "onPrimaryContainer": "#FFFFFF",
            "secondary": "#373447",
            "onSecondary": "#FFFFFF",
            "secondaryContainer": "#6E6A80",
            "onSecondaryContainer": "#FFFFFF",
            "tertiary": "#4F2B3B",
            "onTertiary": "#FFFFFF",
            "tertiaryContainer": "#8C6173",
            "onTertiaryContainer": "#FFFFFF",
            "error": "#740006",
            "onError": "#FFFFFF",
            "errorContainer": "#CF2C27",
            "onErrorContainer": "#FFFFFF",
            "background": "#FDF8FF",
            "onBackground": "#1C1B20",
            "surface": "#FDF8FF",
            "onSurface": "#111016",
            "surfaceVariant": "#E5E0EC",
            "onSurfaceVariant": "#37353E",
            "outline": "#54515A",
            "outlineVariant": "#6E6C75",
            "shadow": "#000000",
            "scrim": "#000000",
            "inverseSurface": "#312F36",
            "inverseOnSurface": "#F4EFF7",
            "inversePrimary": "#C9BFFF",
            "primaryFixed": "#6E65A0",
            "onPrimaryFixed": "#FFFFFF",
            "primaryFixedDim": "#564D86",
            "onPrimaryFixedVariant": "#FFFFFF",
            "secondaryFixed": "#6E6A80",
            "onSecondaryFixed": "#FFFFFF",
            "secondaryFixedDim": "#565267",
            "onSecondaryFixedVariant": "#FFFFFF",
            "tertiaryFixed": "#8C6173",
            "onTertiaryFixed": "#FFFFFF",
            "tertiaryFixedDim": "#71495A",
            "onTertiaryFixedVariant": "#FFFFFF",
            "surfaceDim": "#C9C5CD",
            "surfaceBright": "#FDF8FF",
            "surfaceContainerLowest": "#FFFFFF",
            "surfaceContainerLow": "#F7F2FA",
            "surfaceContainer": "#EBE6EE",
            "surfaceContainerHigh": "#E0DBE3",
            "surfaceContainerHighest": "#D4D0D8"
        },
        "light-high-contrast": {
            "primary": "#2C245A",
            "surfaceTint": "#5F5790",
            "onPrimary": "#FFFFFF",
            "primaryContainer": "#4A417A",
            "onPrimaryContainer": "#FFFFFF",
            "secondary": "#2D2A3D",
            "onSecondary": "#FFFFFF",
            "secondaryContainer": "#4A475B",
            "onSecondaryContainer": "#FFFFFF",
            "tertiary": "#432131",
            "onTertiary": "#FFFFFF",
            "tertiaryContainer": "#643D4F",
            "onTertiaryContainer": "#FFFFFF",
            "error": "#600004",
            "onError": "#FFFFFF",
            "errorContainer": "#98000A",
            "onErrorContainer": "#FFFFFF",
            "background": "#FDF8FF",
            "onBackground": "#1C1B20",
            "surface": "#FDF8FF",
            "onSurface": "#000000",
            "surfaceVariant": "#E5E0EC",
            "onSurfaceVariant": "#000000",
            "outline": "#2D2B33",
            "outlineVariant": "#4A4851",
            "shadow": "#000000",
            "scrim": "#000000",
            "inverseSurface": "#312F36",
            "inverseOnSurface": "#FFFFFF",
            "inversePrimary": "#C9BFFF",
            "primaryFixed": "#4A417A",
            "onPrimaryFixed": "#FFFFFF",
            "primaryFixedDim": "#332A61",
            "onPrimaryFixedVariant": "#FFFFFF",
            "secondaryFixed": "#4A475B",
            "onSecondaryFixed": "#FFFFFF",
            "secondaryFixedDim": "#333044",
            "onSecondaryFixedVariant": "#FFFFFF",
            "tertiaryFixed": "#643D4F",
            "onTertiaryFixed": "#FFFFFF",
            "tertiaryFixedDim": "#4B2738",
            "onTertiaryFixedVariant": "#FFFFFF",
            "surfaceDim": "#BBB7BF",
            "surfaceBright": "#FDF8FF",
            "surfaceContainerLowest": "#FFFFFF",
            "surfaceContainerLow": "#F4EFF7",
            "surfaceContainer": "#E5E1E9",
            "surfaceContainerHigh": "#D7D3DB",
            "surfaceContainerHighest": "#C9C5CD"
        },
        "dark": {
            "primary": "#C9BFFF",
            "surfaceTint": "#C9BFFF",
            "onPrimary": "#31285F",
            "primaryContainer": "#473F77",
            "onPrimaryContainer": "#E5DEFF",
            "secondary": "#C9C3DC",
            "onSecondary": "#312E41",
            "secondaryContainer": "#484459",
            "onSecondaryContainer": "#E5DFF9",
            "tertiary": "#EDB8CD",
            "onTertiary": "#482536",
            "tertiaryContainer": "#623B4C",
            "onTertiaryContainer": "#FFD8E6",
            "error": "#FFB4AB",
            "onError": "#690005",
            "errorContainer": "#93000A",
            "onErrorContainer": "#FFDAD6",
            "background": "#141318",
            "onBackground": "#E5E1E9",
            "surface": "#141318",
            "onSurface": "#E5E1E9",
            "surfaceVariant": "#48454E",
            "onSurfaceVariant": "#C9C5D0",
            "outline": "#938F99",
            "outlineVariant": "#48454E",
            "shadow": "#000000",
            "scrim": "#000000",
            "inverseSurface": "#E5E1E9",
            "inverseOnSurface": "#312F36",
            "inversePrimary": "#5F5790",
            "primaryFixed": "#E5DEFF",
            "onPrimaryFixed": "#1B1149",
            "primaryFixedDim": "#C9BFFF",
            "onPrimaryFixedVariant": "#473F77",
            "secondaryFixed": "#E5DFF9",
            "onSecondaryFixed": "#1C192B",
            "secondaryFixedDim": "#C9C3DC",
            "onSecondaryFixedVariant": "#484459",
            "tertiaryFixed": "#FFD8E6",
            "onTertiaryFixed": "#301120",
            "tertiaryFixedDim": "#EDB8CD",
            "onTertiaryFixedVariant": "#623B4C",
            "surfaceDim": "#141318",
            "surfaceBright": "#3A383E",
            "surfaceContainerLowest": "#0E0D13",
            "surfaceContainerLow": "#1C1B20",
            "surfaceContainer": "#201F25",
            "surfaceContainerHigh": "#2B292F",
            "surfaceContainerHighest": "#36343A"
        },
        "dark-medium-contrast": {
            "primary": "#DFD7FF",
            "surfaceTint": "#C9BFFF",
            "onPrimary": "#261D53",
            "primaryContainer": "#9289C7",
            "onPrimaryContainer": "#000000",
            "secondary": "#DFD9F2",
            "onSecondary": "#262336",
            "secondaryContainer": "#938EA5",
            "onSecondaryContainer": "#000000",
            "tertiary": "#FFD0E2",
            "onTertiary": "#3C1B2B",
            "tertiaryContainer": "#B38397",
            "onTertiaryContainer": "#000000",
            "error": "#FFD2CC",
            "onError": "#540003",
            "errorContainer": "#FF5449",
            "onErrorContainer": "#000000",
            "background": "#141318",
            "onBackground": "#E5E1E9",
            "surface": "#141318",
            "onSurface": "#FFFFFF",
            "surfaceVariant": "#48454E",
            "onSurfaceVariant": "#DFDAE6",
            "outline": "#B4B0BB",
            "outlineVariant": "#928F99",
            "shadow": "#000000",
            "scrim": "#000000",
            "inverseSurface": "#E5E1E9",
            "inverseOnSurface": "#2B292F",
            "inversePrimary": "#494078",
            "primaryFixed": "#E5DEFF",
            "onPrimaryFixed": "#11043F",
            "primaryFixedDim": "#C9BFFF",
            "onPrimaryFixedVariant": "#372E65",
            "secondaryFixed": "#E5DFF9",
            "onSecondaryFixed": "#110F20",
            "secondaryFixedDim": "#C9C3DC",
            "onSecondaryFixedVariant": "#373447",
            "tertiaryFixed": "#FFD8E6",
            "onTertiaryFixed": "#240616",
            "tertiaryFixedDim": "#EDB8CD",
            "onTertiaryFixedVariant": "#4F2B3B",
            "surfaceDim": "#141318",
            "surfaceBright": "#45434A",
            "surfaceContainerLowest": "#08070C",
            "surfaceContainerLow": "#1E1D22",
            "surfaceContainer": "#28272D",
            "surfaceContainerHigh": "#333238",
            "surfaceContainerHighest": "#3F3D43"
        },
        "dark-high-contrast": {
            "primary": "#F3EDFF",
            "surfaceTint": "#C9BFFF",
            "onPrimary": "#000000",
            "primaryContainer": "#C5BBFC",
            "onPrimaryContainer": "#0B0037",
            "secondary": "#F3EDFF",
            "onSecondary": "#000000",
            "secondaryContainer": "#C5BFD8",
            "onSecondaryContainer": "#0B091A",
            "tertiary": "#FFEBF1",
            "onTertiary": "#000000",
            "tertiaryContainer": "#E9B4C9",
            "onTertiaryContainer": "#1C0210",
            "error": "#FFECE9",
            "onError": "#000000",
            "errorContainer": "#FFAEA4",
            "onErrorContainer": "#220001",
            "background": "#141318",
            "onBackground": "#E5E1E9",
            "surface": "#141318",
            "onSurface": "#FFFFFF",
            "surfaceVariant": "#48454E",
            "onSurfaceVariant": "#FFFFFF",
            "outline": "#F3EEF9",
            "outlineVariant": "#C5C1CC",
            "shadow": "#000000",
            "scrim": "#000000",
            "inverseSurface": "#E5E1E9",
            "inverseOnSurface": "#000000",
            "inversePrimary": "#494078",
            "primaryFixed": "#E5DEFF",
            "onPrimaryFixed": "#000000",
            "primaryFixedDim": "#C9BFFF",
            "onPrimaryFixedVariant": "#11043F",
            "secondaryFixed": "#E5DFF9",
            "onSecondaryFixed": "#000000",
            "secondaryFixedDim": "#C9C3DC",
            "onSecondaryFixedVariant": "#110F20",
            "tertiaryFixed": "#FFD8E6",
            "onTertiaryFixed": "#000000",
            "tertiaryFixedDim": "#EDB8CD",
            "onTertiaryFixedVariant": "#240616",
            "surfaceDim": "#141318",
            "surfaceBright": "#514F56",
            "surfaceContainerLowest": "#000000",
            "surfaceContainerLow": "#201F25",
            "surfaceContainer": "#312F36",
            "surfaceContainerHigh": "#3C3A41",
            "surfaceContainerHighest": "#48464C"
        }
    },
    "palettes": {
        "primary": {
            "0": "#000000",
            "5": "#100046",
            "10": "#1A0063",
            "15": "#24007F",
            "20": "#2F009C",
            "25": "#3A00BA",
            "30": "#451CC8",
            "35": "#512FD3",
            "40": "#5E3FDF",
            "50": "#775CFA",
            "60": "#927EFF",
            "70": "#AD9FFF",
            "80": "#C9BFFF",
            "90": "#E5DEFF",
            "95": "#F4EEFF",
            "98": "#FDF8FF",
            "99": "#FFFBFF",
            "100": "#FFFFFF"
        },
        "secondary": {
            "0": "#000000",
            "5": "#110C2B",
            "10": "#1C1736",
            "15": "#262141",
            "20": "#312C4D",
            "25": "#3C3758",
            "30": "#484265",
            "35": "#534E71",
            "40": "#605A7E",
            "50": "#797298",
            "60": "#938CB2",
            "70": "#ADA6CE",
            "80": "#C9C1EA",
            "90": "#E5DEFF",
            "95": "#F4EEFF",
            "98": "#FDF8FF",
            "99": "#FFFBFF",
            "100": "#FFFFFF"
        },
        "tertiary": {
            "0": "#000000",
            "5": "#2A0018",
            "10": "#390623",
            "15": "#46112E",
            "20": "#531C39",
            "25": "#612744",
            "30": "#6E3350",
            "35": "#7C3E5C",
            "40": "#8A4A68",
            "50": "#A66281",
            "60": "#C37B9B",
            "70": "#E195B6",
            "80": "#FFAFD1",
            "90": "#FFD8E6",
            "95": "#FFECF1",
            "98": "#FFF8F8",
            "99": "#FFFBFF",
            "100": "#FFFFFF"
        },
        "neutral": {
            "0": "#000000",
            "5": "#111014",
            "10": "#1C1B1F",
            "15": "#262529",
            "20": "#313033",
            "25": "#3C3B3F",
            "30": "#48464A",
            "35": "#545256",
            "40": "#605D62",
            "50": "#79767A",
            "60": "#939094",
            "70": "#ADAAAF",
            "80": "#C9C5CA",
            "90": "#E5E1E6",
            "95": "#F4EFF4",
            "98": "#FDF8FD",
            "99": "#FFFBFF",
            "100": "#FFFFFF"
        },
        "neutral-variant": {
            "0": "#000000",
            "5": "#111018",
            "10": "#1C1B22",
            "15": "#26252D",
            "20": "#312F38",
            "25": "#3C3A43",
            "30": "#48454E",
            "35": "#54515A",
            "40": "#605D66",
            "50": "#79757F",
            "60": "#938F99",
            "70": "#ADA9B4",
            "80": "#C9C5D0",
            "90": "#E5E0EC",
            "95": "#F4EFFA",
            "98": "#FDF8FF",
            "99": "#FFFBFF",
            "100": "#FFFFFF"
        }
    }
}